{
  "id": "p_1bd4fe606660",
  "createdAt": 1776608648989,
  "updatedAt": 1776609913504,
  "coins": 500,
  "treasures": {},
  "ownedBombermen": [],
  "equippedBombermanId": null,
  "bombStockpile": {},
  "gamblerStreet": {
    "gamblers": [],
    "pendingArrivals": [
      1777330178901,
      1777330178901,
      1777330178901,
      1777330178901,
      1777330178901
    ],
    "lastTickedAt": 1777330178901,
    "nextGamblerSerial": 1
  },
  "bombermanShop": null,
  "factories": {
    "1": {
      "firstCycleStartedAt": null,
      "queueLength": 0,
      "storage": []
    },
    "2": {
      "firstCycleStartedAt": null,
      "queueLength": 0,
      "storage": []
    },
    "3": {
      "firstCycleStartedAt": null,
      "queueLength": 0,
      "storage": []
    },
    "4": {
      "firstCycleStartedAt": null,
      "queueLength": 0,
      "storage": []
    }
  }
}